pbt/__init__.py
pbt/__main__.py
pbt/config.py
pbt/console/__init__.py
pbt/console/git.py
pbt/console/pbt.py
pbt/diff.py
pbt/misc.py
pbt/package/__init__.py
pbt/package/graph.py
pbt/package/manager/__init__.py
pbt/package/manager/manager.py
pbt/package/manager/maturin.py
pbt/package/manager/poetry.py
pbt/package/manager/python.py
pbt/package/package.py
pbt/package/pipeline.py
pbt/package/registry/__init__.py
pbt/package/registry/pypi.py
pbt/package/registry/registry.py
pbt/vcs/__init__.py
pbt/vcs/git.py
pbt-2.13.0.dist-info/METADATA
pbt-2.13.0.dist-info/WHEEL
pbt-2.13.0.dist-info/entry_points.txt
pbt-2.13.0.dist-info/RECORD
