Metadata-Version: 2.1
Name: pbt
Version: 2.13.0
Summary: A build tool for multiple Python projects in a single repository
Home-page: https://github.com/binh-vu/pbt
License: MIT
Author: Binh Vu
Author-email: binh@toan2.com
Requires-Python: >=3.8,<4.0
Classifier: License :: OSI Approved :: MIT License
Classifier: Programming Language :: Python :: 3
Classifier: Programming Language :: Python :: 3.8
Classifier: Programming Language :: Python :: 3.9
Classifier: Programming Language :: Python :: 3.10
Classifier: Programming Language :: Python :: 3.11
Requires-Dist: click (>=8.1.3,<9.0.0)
Requires-Dist: hugedict (>=2.9.2,<3.0.0)
Requires-Dist: loguru (>=0.6.0,<0.7.0)
Requires-Dist: maturin (>=1.0.1,<2.0.0)
Requires-Dist: networkx (>=2.8.2,<3.0.0)
Requires-Dist: orjson (>=3.9.0,<4.0.0)
Requires-Dist: poetry (>=1.5.1,<2.0.0)
Requires-Dist: requests (>=2.28.0,<3.0.0)
Requires-Dist: semver (>=2.13.0,<3.0.0)
Requires-Dist: tomlkit (>=0.11.5,<0.12.0)
Requires-Dist: typing-extensions (>=4.4.0,<5.0.0)
Project-URL: Repository, https://github.com/binh-vu/pbt
